watiba/__init__.py
watiba/version.py
watiba/watiba-c-bin.py
watiba/watiba-c.py
watiba/watiba.py
watiba/wtoutput.py
watiba/wtpromise.py
watiba/wtspawncontroller.py
watiba-0.4.48.dist-info/LICENSE
watiba-0.4.48.dist-info/METADATA
watiba-0.4.48.dist-info/WHEEL
watiba-0.4.48.dist-info/top_level.txt
watiba-0.4.48.dist-info/RECORD
