Metadata-Version: 2.1
Name: watiba
Version: 0.4.48
Summary: Python syntactical sugar for embedded shell commands
Home-page: https://github.com/Raythonic/watiba
Author: Ray Walker
Author-email: raythonic@gmail.com
License: MIT
Platform: UNKNOWN
Classifier: Programming Language :: Python :: 3
Classifier: License :: OSI Approved :: MIT License
Classifier: Operating System :: OS Independent
Requires-Python: >=3.8
